time_int/__init__.py
time_int/time_int.py
time_int-0.0.9.dist-info/WHEEL
time_int-0.0.9.dist-info/METADATA
time_int-0.0.9.dist-info/RECORD
