Metadata-Version: 2.1
Name: time-int
Version: 0.0.9
Summary: Subclass of integer representing seconds since UNIX epoch
Home-page: https://github.com/aallaire/time-int
License: MIT
Author: Andrew Allaire
Author-email: andrew.allaire@gmail.com
Requires-Python: >=3.5,<4.0
Classifier: License :: OSI Approved :: MIT License
Classifier: Programming Language :: Python :: 3
Classifier: Programming Language :: Python :: 3.5
Classifier: Programming Language :: Python :: 3.6
Classifier: Programming Language :: Python :: 3.7
Classifier: Programming Language :: Python :: 3.8
Requires-Dist: magic-kind (>=0.2.2,<0.3.0)
Requires-Dist: pytest (>=5.4.2,<6.0.0)
Project-URL: Repository, https://github.com/aallaire/time-int
